OpenAISurveyWrapper/None.py
OpenAISurveyWrapper/__init__.py
OpenAISurveyWrapper/_nbdev.py
OpenAISurveyWrapper/evaluate.py
OpenAISurveyWrapper/evaluateSearch.py
OpenAISurveyWrapper/survey.py
OpenAISurveyWrapper/wrapper.py
OpenAISurveyWrapper-0.0.9.dist-info/LICENSE
OpenAISurveyWrapper-0.0.9.dist-info/METADATA
OpenAISurveyWrapper-0.0.9.dist-info/WHEEL
OpenAISurveyWrapper-0.0.9.dist-info/entry_points.txt
OpenAISurveyWrapper-0.0.9.dist-info/top_level.txt
OpenAISurveyWrapper-0.0.9.dist-info/RECORD
