Metadata-Version: 2.1
Name: OpenAISurveyWrapper
Version: 0.0.9
Summary: wrapper for the OpenAI to label survey results
Home-page: https://github.com/brockmanmatt/OpenAISurveyWrapper/tree/master/
Author: Matt Brockman
Author-email: brockman@email.arizona.edu
License: Apache Software License 2.0
Keywords: topic modeling
Platform: UNKNOWN
Classifier: Development Status :: 3 - Alpha
Classifier: Intended Audience :: Developers
Classifier: License :: OSI Approved :: Apache Software License
Classifier: Natural Language :: English
Classifier: Programming Language :: Python :: 3.6
Classifier: Programming Language :: Python :: 3.7
Classifier: Programming Language :: Python :: 3.8
Requires-Python: >=3.6
Requires-Dist: openai
Requires-Dist: pandas
Requires-Dist: numpy
Requires-Dist: scikit-learn
